{
    "bandhan large cap fund": {
        "amc_name": "",
        "benchmark_index": "BSE 100 TRI (w.e.f. April 18, 2017)",
        "fund_manager": "Mr. Manish Gunwani and Mr. Prateek Poddar (w.e.f. 02nd December 2024)",
        "inception_date": "9 June 2006",
        "load": {
            "exit_load": " If redeemed/switched out on/within 30 days from the date of allotment - 0.5% of the applicable NAV.  If redeemed/switched out after 30 days from the date of allotment - Nil."
        },
        "main_scheme_name": "bandhan large cap fund",
        "metrics.beta": "0.99",
        "metrics.r_squared": "0.94",
        "metrics.standard_deviation": "13.33",
        "minimum_investment": "1,000/- and any amount",
        "monthly_aaum_date": "2 8   F E B R U A R Y   2 0 2 5",
        "monthly_avg_aum": "1,790.47 Crores",
        "mutual_fund_name": "",
        "page_number": [
            17
        ]
    },
    "bandhan small cap fund": {
        "amc_name": "",
        "benchmark_index": "BSE 250 SmallCap TRI",
        "fund_manager": "Mr. Manish Gunwani (w.e.f. 28 January, 2023), Mr. Kirthi Jain (w.e.f. 05 June, 2023).",
        "inception_date": "25 February 2020",
        "load": {
            "exit_load": "1% if redeemed/switched out within 1 year from the date of allotment"
        },
        "main_scheme_name": "bandhan small cap fund",
        "metrics.beta": "0.90",
        "metrics.r_squared": "0.90",
        "metrics.standard_deviation": "16.77",
        "minimum_investment": "1,000/- and any amount",
        "monthly_aaum_date": "2 8   F E B R U A R Y   2 0 2 5",
        "monthly_avg_aum": "9,646.67 Crores",
        "mutual_fund_name": "",
        "page_number": [
            18
        ]
    },
    "bandhan core equity fund": {
        "amc_name": "",
        "benchmark_index": "NIFTY LargeMidcap 250 TRI (w.e.f. 7th October 2019)",
        "fund_manager": "Mr. Manish Gunwani (w.e.f. 28 January, 2023), Rahul Agarwal (w.e.f. 28 August, 2023).",
        "inception_date": "9 August 2005",
        "load": {
            "exit_load": " If redeemed/switched out within 365 days from the date of allotment:  Upto 10% of investment:Nil,  For remaining investment: 1% of applicable NAV.  If redeemed / switched out after 365 days from date of allotment: Nil. (w.e.f. May 08, 2020)"
        },
        "main_scheme_name": "bandhan core equity fund",
        "metrics.beta": "0.95",
        "metrics.r_squared": "0.94",
        "metrics.standard_deviation": "13.77",
        "minimum_investment": "1,000/- and any amount",
        "monthly_aaum_date": "2 8   F E B R U A R Y   2 0 2 5",
        "monthly_avg_aum": "7,589.48 Crores",
        "mutual_fund_name": "",
        "page_number": [
            19
        ]
    },
    "bandhan flexi cap fund": {
        "amc_name": "",
        "benchmark_index": "BSE 500 TRI",
        "fund_manager": "Mr. Manish Gunwani & Mr. Viraj Kulkarni (w.e.f. 24th January, 2024).",
        "inception_date": "28 September 2005",
        "load": {
            "exit_load": " If redeemed/switched out within 365 days from the date of allotment:  Upto 10% of investment:Nil,  For remaining investment: 1% of applicable NAV.  If redeemed / switched out after 365 days from date of allotment: Nil. (w.e.f. May 08, 2020)"
        },
        "main_scheme_name": "bandhan flexi cap fund",
        "metrics.beta": "0.93",
        "metrics.r_squared": "0.92",
        "metrics.standard_deviation": "13.18",
        "minimum_investment": "1,000/- and any amount (Units of Bandhan Flexi Cap Fund, shall be available for lump sum subscription w.e.f. May 07, 2018)",
        "monthly_aaum_date": "2 8   F E B R U A R Y   2 0 2 5",
        "monthly_avg_aum": "7,327.55 Crores",
        "mutual_fund_name": "",
        "page_number": [
            20
        ]
    },
    "bandhan multi cap fund": {
        "amc_name": "",
        "benchmark_index": "NIFTY 500 Multicap 50:25:25 TRI",
        "fund_manager": "Mr. Daylynn Pinto (equity portion), Mr. Harshal Joshi (debt portion).",
        "inception_date": "2 December, 2021",
        "load": {
            "exit_load": "If redeemed/switched out within 1 year from the date of allotment -1% of applicable NAV; If redeemed/ switched out after 1 year from the date of allotment Nil"
        },
        "main_scheme_name": "bandhan multi cap fund",
        "minimum_investment": "Rs 1,000/- and any amount",
        "monthly_aaum_date": "2 8   F E B R U A R Y   2 0 2 5",
        "monthly_avg_aum": "2,483.02 Crores",
        "mutual_fund_name": "",
        "page_number": [
            21
        ]
    },
    "bandhan midcap fund": {
        "amc_name": "",
        "benchmark_index": "BSE 150 Midcap TRI",
        "fund_manager": "Ms. Ritu Modi (w.e.f. 16th November 2022) (equity portion), Mr. Harshal Joshi (debt portion).",
        "inception_date": "18 August, 2022",
        "load": {
            "exit_load": "If redeemed/switched out within 1 year from the date of allotment - 1% of applicable NAV; If redeemed/switched out after 1 year from the date of allotment  Nil"
        },
        "main_scheme_name": "bandhan midcap fund",
        "minimum_investment": "Rs 1,000/- and any amount",
        "monthly_aaum_date": "2 8   F E B R U A R Y   2 0 2 5",
        "monthly_avg_aum": "1,612.52 Crores",
        "mutual_fund_name": "",
        "page_number": [
            22
        ]
    },
    "bandhan elss tax saver fund": {
        "amc_name": "",
        "benchmark_index": "BSE 500 TRI (w.e.f. 1st Dec, 2021)",
        "fund_manager": "Mr. Daylynn Pinto (w.e.f. 20th October 2016).",
        "inception_date": "26 December 2008",
        "load": {
            "exit_load": "Nil"
        },
        "main_scheme_name": "bandhan elss tax saver fund",
        "metrics.beta": "0.92",
        "metrics.r_squared": "0.94",
        "metrics.standard_deviation": "12.97",
        "minimum_investment": "500/- and in multiples of 500/- thereafter.",
        "monthly_aaum_date": "2 8   F E B R U A R Y   2 0 2 5",
        "monthly_avg_aum": "6,948.88 Crores",
        "mutual_fund_name": "",
        "page_number": [
            23
        ]
    },
    "bandhan focused equity fund": {
        "amc_name": "",
        "benchmark_index": "BSE 500 TRI (with effect from November 11, 2019)",
        "fund_manager": "Mr. Manish Gunwani, Mr. Kirthi Jain and Mr. Rahul Agarwal (w.e.f. December 02, 2024).",
        "inception_date": "16 March 2006",
        "load": {
            "exit_load": " If redeemed/switched out within 365 days from the date of allotment:  Upto 10% of investment:Nil,  For remaining investment: 1% of applicable NAV.  If redeemed / switched out after 365 days from date of allotment: Nil. (w.e.f. May 08, 2020)"
        },
        "main_scheme_name": "bandhan focused equity fund",
        "metrics.beta": "0.89",
        "metrics.r_squared": "0.77",
        "metrics.standard_deviation": "13.69",
        "minimum_investment": "$ 1,000/- and any amount",
        "monthly_aaum_date": "2 8   F E B R U A R Y   2 0 2 5",
        "monthly_avg_aum": "1,843.44 Crores",
        "mutual_fund_name": "",
        "page_number": [
            24
        ]
    },
    "bandhan sterling value fund": {
        "amc_name": "",
        "benchmark_index": "ModerateMoHdeigrhately Low to Moderate High Very Low High Riskometer The risk of the benchmark is very high. Tier 2: BSE 400 MidSmallCap TRI",
        "fund_manager": "Mr. Daylynn Pinto (w.e.f. 20th October 2016).",
        "inception_date": "7 March 2008",
        "load": {
            "exit_load": " If redeemed/switched out within 365 days from the date of allotment:  Upto 10% of investment:Nil,  For remaining investment: 1% of applicable NAV.  If redeemed / switched out after 365 days from date of allotment: Nil. (w.e.f. May 08, 2020)"
        },
        "main_scheme_name": "bandhan sterling value fund",
        "metrics.beta": "0.94",
        "metrics.r_squared": "0.91",
        "metrics.standard_deviation": "13.37",
        "minimum_investment": "1,000/- and any amount",
        "monthly_aaum_date": "2 8   F E B R U A R Y   2 0 2 5",
        "monthly_avg_aum": "10,116.62 Crores",
        "mutual_fund_name": "",
        "page_number": [
            25
        ]
    },
    "bandhan infrastructure fund": {
        "amc_name": "",
        "benchmark_index": "BSE India Infrastructure TRI (with effect from November 11, 2019)",
        "fund_manager": "Mr. Vishal Biraia (w.e.f. 24th January 2024)",
        "inception_date": "8 March 2011",
        "load": {
            "exit_load": " If redeemed/switched out on/within 30 days from the date of allotment - 0.5% of the applicable NAV.  If redeemed/switched out after 30 days from the date of allotment - Nil."
        },
        "main_scheme_name": "bandhan infrastructure fund",
        "metrics.beta": "0.61",
        "metrics.r_squared": "0.70",
        "metrics.standard_deviation": "17.13",
        "minimum_investment": "1,000/- and any amount",
        "monthly_aaum_date": "2 8   F E B R U A R Y   2 0 2 5",
        "monthly_avg_aum": "1,826.42 Crores",
        "mutual_fund_name": "",
        "page_number": [
            26
        ]
    },
    "bandhan transportation and logistics fund": {
        "amc_name": "",
        "benchmark_index": "Nifty Transportation and Logistics TRI",
        "fund_manager": "Mr. Daylynn Pinto (equity portion), Mr. Harshal Joshi (debt portion).",
        "inception_date": "27 October 2022",
        "load": {
            "exit_load": " If redeemed/switched out on/within 30 days from the date of allotment - 0.5% of the applicable NAV.  If redeemed/switched out after 30 days from the date of allotment - Nil."
        },
        "main_scheme_name": "bandhan transportation and logistics fund",
        "minimum_investment": "1,000/- and in multiples of Re. 1/- thereafter",
        "monthly_aaum_date": "2 8   F E B R U A R Y   2 0 2 5",
        "monthly_avg_aum": "545.51 Crores",
        "mutual_fund_name": "",
        "page_number": [
            27
        ]
    },
    "bandhan financial services fund": {
        "amc_name": "",
        "benchmark_index": "Nifty Financial Services TRI",
        "fund_manager": "Ms. Ritu Modi (w.e.f. December 02, 2024) Mr. Harshvardhan Agarwal (w.e.f. June 07, 2024 (equity portion)). Mr. Harshal Joshi (debt portion).",
        "inception_date": "28-July-2023",
        "load": {
            "exit_load": " If redeemed/switched out on/within 30 days from the date of allotment - 0.5% of the applicable NAV.  If redeemed/switched out after 30 days from the date of allotment - Nil."
        },
        "main_scheme_name": "bandhan financial services fund",
        "minimum_investment": "1,000/- and in multiples of Re. 1/- thereafter",
        "monthly_aaum_date": "2 8   F E B R U A R Y   2 0 2 5",
        "monthly_avg_aum": "971.40 Crores",
        "mutual_fund_name": "",
        "page_number": [
            28
        ]
    },
    "bandhan innovation fund": {
        "amc_name": "",
        "benchmark_index": "Nifty 500 TRI",
        "fund_manager": "Mr. Manish Gunwani & Mr. Prateek Poddar w.e.f. June 07, 2024 (equity portion), Mr. Brijesh Shah (debt portion).",
        "inception_date": "30-April-2024",
        "load": {
            "exit_load": " If redeemed/switched out within 30 days from the date of allotment: 0.50% of the applicable NAV.  If redeemed/switched out after 30 days from date of allotment  Nil."
        },
        "main_scheme_name": "bandhan innovation fund",
        "minimum_investment": "1,000/- and in multiples of Re. 1/- thereafter",
        "monthly_aaum_date": "2 8   F E B R U A R Y   2 0 2 5",
        "monthly_avg_aum": "1,397.72 Crores",
        "mutual_fund_name": "",
        "page_number": [
            29
        ]
    },
    "bandhan business cycle fund": {
        "amc_name": "",
        "benchmark_index": "Nifty 500 TRI",
        "fund_manager": "Mr. Vishal Biraia, Ms. Ritika Behera (equity portion), Mr. Harshal Joshi (debt portion).",
        "inception_date": "30-September-2024",
        "load": {
            "exit_load": " If redeemed/switched out on/within 30 days from the date of allotment - 0.5% of applicable NAV.  If redeemed/switched out after 30 days from the date of allotment  Nil."
        },
        "main_scheme_name": "bandhan business cycle fund",
        "minimum_investment": "1,000/- and in multiples of Re. 1/- thereafter",
        "monthly_aaum_date": "2 8   F E B R U A R Y   2 0 2 5",
        "monthly_avg_aum": "1,730.39 Crores",
        "mutual_fund_name": "",
        "page_number": [
            30
        ]
    },
    "bandhan arbitrage fund": {
        "amc_name": "",
        "benchmark_index": "Nifty 50 Arbitrage Index (w.e.f. April 01, 2018)",
        "fund_manager": "Mr. Nemish Sheth (w.e.f. 1st November 2021) & Mr. Harshal Joshi",
        "inception_date": "21 December 2006",
        "load": {
            "exit_load": " If redeemed/switched out on or before 15 days from the date of allotment - 0.25%  If redeemed/switched out after 15 days from the date of allotment - NIL (w.e.f 01st April 2024)"
        },
        "main_scheme_name": "bandhan arbitrage fund",
        "metrics.beta": "0.76",
        "metrics.r_squared": "0.74",
        "metrics.standard_deviation": "0.60",
        "minimum_investment": "100/- and any amount",
        "monthly_aaum_date": "2 8   F E B R U A R Y   2 0 2 5",
        "monthly_avg_aum": "7,592.95 Crores",
        "mutual_fund_name": "",
        "page_number": [
            31,
            32
        ]
    },
    "bandhan equity savings fund": {
        "amc_name": "",
        "benchmark_index": "CRISIL Equity Savings Index (w.e.f. 1st Dec, 2021)",
        "fund_manager": "Mr. Nemish Sheth & Mr. Viraj Kulkarni (w.e.f. 1st July 2022)",
        "inception_date": "9 June 2008",
        "load": {
            "exit_load": "If redeemed/switched out within 7 days from the date of allotment:  Up to 10% of investment: Nil,  For remaining investment: 0.25% of applicable NAV.  If redeemed/switched out after 7 days from date of allotment: Nil."
        },
        "main_scheme_name": "bandhan equity savings fund",
        "metrics.average_maturity": "2.64",
        "metrics.beta": "0.56",
        "metrics.macaulay_duration": "2.12",
        "metrics.modified_duration": "2.05",
        "metrics.r_squared": "0.90",
        "metrics.standard_deviation": "2.75",
        "metrics.yield_to_maturity": "7.23",
        "minimum_investment": "1,000/- and any amount",
        "monthly_aaum_date": "2 8   F E B R U A R Y   2 0 2 5",
        "monthly_avg_aum": "250.95 Crores",
        "mutual_fund_name": "",
        "page_number": [
            33
        ]
    },
    "bandhan balanced advantage fund": {
        "amc_name": "",
        "benchmark_index": "NIFTY 50 Hybrid Composite debt 50:50 Index (w.e.f. 1st Dec, 2021)",
        "fund_manager": ": Mr. Manish Gunwani (w.e.f. 24th january 2024) & Mr. Vishal Biraia (w.e.f. December 02, 2024).",
        "inception_date": "10 October 2014",
        "load": {
            "exit_load": "In respect of each purchase of Units: - For 10% of investment: Nil - For remaining investment: 1% if redeemed/ switched out within 1 year from the date of allotment (w.e.f. July 5, 2017)"
        },
        "main_scheme_name": "bandhan balanced advantage fund",
        "metrics.average_maturity": "11.37",
        "metrics.beta": "0.93",
        "metrics.macaulay_duration": "6.17",
        "metrics.modified_duration": "5.96",
        "metrics.r_squared": "0.82",
        "metrics.standard_deviation": "7.10",
        "metrics.yield_to_maturity": "7.20",
        "minimum_investment": "1,000/- and any amount",
        "monthly_aaum_date": "2 8   F E B R U A R Y   2 0 2 5",
        "monthly_avg_aum": "2,291.17 Crores",
        "mutual_fund_name": "",
        "page_number": [
            34
        ]
    },
    "bandhan multi asset allocation fund": {
        "amc_name": "",
        "benchmark_index": "65% Nifty 500 TRI + 25% NIFTY Short Duration Debt Index + 5% Domestic prices of gold + 5% Domestic prices of silver",
        "fund_manager": ": Mr. Viraj Kulkarni, Mr. Daylynn Pinto & Mr. Nemish Sheth.",
        "inception_date": "31 January 2024",
        "load": {
            "exit_load": " For 10% of investment: NIL  For remaining investment:  0.50% if redeemed/ switched out within 1 year from the date of allotment.  If redeemed/switched out after 1 year from the date of allotment - NIL (w.e.f 01st April 2024)"
        },
        "main_scheme_name": "bandhan multi asset allocation fund",
        "metrics.average_maturity": "16.31",
        "metrics.macaulay_duration": "7.19",
        "metrics.modified_duration": "6.95",
        "metrics.yield_to_maturity": "6.77",
        "minimum_investment": "1,000/- and in multiples of Re. 1/- thereafter",
        "monthly_aaum_date": "2 8   F E B R U A R Y   2 0 2 5",
        "monthly_avg_aum": "1,822.29 Crores",
        "mutual_fund_name": "",
        "page_number": [
            35
        ]
    },
    "bandhan hybrid equity fund": {
        "amc_name": "",
        "benchmark_index": "CRISIL Hybrid 35+65 Aggressive Index (w.e.f. 1st Dec, 2021)",
        "fund_manager": "Mr. Prateek Poddar (w.e.f. 07 June 2024) Mr. Harshal Joshi.",
        "inception_date": "30 December 2016",
        "load": {
            "exit_load": "10% of investment: Nil"
        },
        "main_scheme_name": "bandhan hybrid equity fund",
        "metrics.average_maturity": "12.49",
        "metrics.beta": "1.07",
        "metrics.macaulay_duration": "6.01",
        "metrics.modified_duration": "5.79",
        "metrics.r_squared": "0.88",
        "metrics.standard_deviation": "10.45",
        "metrics.yield_to_maturity": "7.39",
        "minimum_investment": "1,000/- and any amount",
        "monthly_aaum_date": "2 8   F E B R U A R Y   2 0 2 5",
        "monthly_avg_aum": "826.40 Crores",
        "mutual_fund_name": "",
        "page_number": [
            36
        ]
    },
    "bandhan retirement fund": {
        "amc_name": "",
        "benchmark_index": "CRISIL Hybrid 50+50 - Moderate Index",
        "fund_manager": "Mr. Vishal Biraia (w.e.f. 24 January, 2024) & Mr. Viraj Kulkarni (w.e.f. December 02, 2024) Mr. Gautam Kaul (w.e.f. 19th October",
        "inception_date": "13 October 2023",
        "load": {
            "exit_load": "Nil"
        },
        "main_scheme_name": "bandhan retirement fund",
        "metrics.average_maturity": "23.33",
        "metrics.macaulay_duration": "10.29",
        "metrics.modified_duration": "9.94",
        "metrics.yield_to_maturity": "6.98",
        "minimum_investment": "1,000/- and in multiples of Re. 1/- thereafter",
        "monthly_aaum_date": "2 8   F E B R U A R Y   2 0 2 5",
        "monthly_avg_aum": "175.57 Crores",
        "mutual_fund_name": "",
        "page_number": [
            37
        ]
    },
    "bandhan conservative hybrid fund": {
        "amc_name": "",
        "benchmark_index": "CRISIL Hybrid 85+15 Conservative Index (w.e.f. 1st Dec, 2021)",
        "fund_manager": "Mr. Viraj Kulkarni &",
        "inception_date": "25 February 2010",
        "load": {
            "exit_load": " If redeemed/switched out within 7 days from the date of allotment: - Up to 10% of investment: Nil, for remaining investment: 0.25% of applicable NAV.  If redeemed/switched out after 7 days from date of allotment: Nil."
        },
        "main_scheme_name": "bandhan conservative hybrid fund",
        "metrics.average_maturity": "12.26",
        "metrics.macaulay_duration": "6.09",
        "metrics.modified_duration": "5.87",
        "metrics.standard_deviation": "3.84",
        "metrics.yield_to_maturity": "7.22",
        "minimum_investment": "1,000/- and any amount",
        "monthly_aaum_date": "2 8   F E B R U A R Y   2 0 2 5",
        "monthly_avg_aum": "118.91 Crores",
        "mutual_fund_name": "",
        "page_number": [
            38
        ]
    },
    "bandhan us equity fund of fund": {
        "amc_name": "",
        "benchmark_index": "Russell 1000 Growth Index (Total Return Net of 30% withholding tax)",
        "fund_manager": "Ms. Ritika Behera (w.e.f. 7th October 2023) & Mr. Gaurav Satra (w.e.f. 7th June 2024)",
        "inception_date": "20 August 2021",
        "load": {
            "exit_load": "1% of applicable NAV - if the units are redeemed/switched out within 1 year from the date of allotment Nil  if the units are redeemed / switched-out after 1 year from the date of allotment"
        },
        "main_scheme_name": "bandhan us equity fund of fund",
        "minimum_investment": "Fresh Purchase (including switch-in) - 1,000/- and in multiples of Re. 1/- thereafter Additional Purchase (including switch-in) - Rs.1,000/- and any amount thereafter",
        "monthly_aaum_date": "2 8   F E B R U A R Y   2 0 2 5",
        "monthly_avg_aum": "352.42 Crores",
        "mutual_fund_name": "",
        "page_number": [
            39
        ]
    },
    "bandhan us treasury bond 0-1 year fund of fund": {
        "amc_name": "",
        "benchmark_index": "ICE 0-1 Year US Treasury Securities Index",
        "fund_manager": "Mr. Brijesh Shah (Overseas and Debt portion).",
        "inception_date": "28 March 2023",
        "load": {
            "exit_load": "0.10% of applicable NAV - if the units are redeemed/switched out within seven days from the date of allotment; Nil - if the units are redeemed/switched out after 7 days from the date of allotment."
        },
        "main_scheme_name": "bandhan us treasury bond 0-1 year fund of fund",
        "minimum_investment": "Fresh Purchase (including switch-in) - 1,000/- and in multiples of Re. 1/- thereafter Additional Purchase (including switch-in) - Rs.1,000/- and any amount thereafter",
        "monthly_aaum_date": "2 8   F E B R U A R Y   2 0 2 5",
        "monthly_avg_aum": "141.46 Crores",
        "mutual_fund_name": "",
        "page_number": [
            40
        ]
    },
    "bandhan asset allocation fund of funds": {
        "amc_name": "",
        "benchmark_index": "PPOORRTTFFOOLLIOIO ModerateMoHdeigrhately Low to Moderate High Very Low High Riskometer The risk of the benchmark is moderately high. CRISIL Hybrid 85+15 Conservative Index",
        "fund_manager": "Mr. Viraj Kulkarni (w.e.f. July 1, 2022)",
        "inception_date": "11 February 2010",
        "load": {
            "exit_load": "*Since InceptioIfn r eRdeegeumlaer dP/slawni t-c hGerdo wotuht Fweitbh i1n1 3, 6250 1d0a.ys from the date of allotment:  Upto 10% of investment:Nil,  For remaining investment: 1% of applicable NAV.  If redeemed / switched out after 365 days from date of allotment: Nil. (w.e.f. May 08, 2020)"
        },
        "main_scheme_name": "bandhan asset allocation fund of funds",
        "minimum_investment": "1,000/- and any amount",
        "monthly_aaum_date": "2 8   F E B R U A R Y   2 0 2 5",
        "monthly_avg_aum": "6.05 Crores",
        "mutual_fund_name": "",
        "page_number": [
            41,
            42
        ]
    },
    "bandhan all seasons bond fund": {
        "amc_name": "",
        "benchmark_index": "NIFTY Medium Duration Debt Index A-III (w.e.f. 1st April 2022) NIFTY Short Duration Debt",
        "fund_manager": "Mr. Harshal Joshi (w.e.f 15th July 2016)",
        "inception_date": "13 September 2004",
        "load": {
            "exit_load": "Nil (w.e.f. 11 November, 2020)"
        },
        "main_scheme_name": "bandhan all seasons bond fund",
        "metrics.average_maturity": "3.62",
        "metrics.macaulay_duration": "3.01",
        "metrics.modified_duration": "2.89",
        "metrics.standard_deviation": "0.66",
        "metrics.yield_to_maturity": "7.31",
        "minimum_investment": "1,000/- and any amount",
        "monthly_aaum_date": "2 8   F E B R U A R Y   2 0 2 5",
        "monthly_avg_aum": "112.91 Crores",
        "mutual_fund_name": "",
        "page_number": [
            43
        ]
    },
    "bandhan overnight fund": {
        "amc_name": "",
        "benchmark_index": "Nifty 1D Rate Index",
        "fund_manager": "Mr. Brijesh Shah (w.e.f. 1st February 2019).",
        "inception_date": "18 January 2019",
        "load": {
            "exit_load": "Nil."
        },
        "main_scheme_name": "bandhan overnight fund",
        "metrics.average_maturity": "1",
        "metrics.macaulay_duration": "1",
        "metrics.modified_duration": "1",
        "metrics.standard_deviation": "0.12",
        "metrics.yield_to_maturity": "6.68",
        "minimum_investment": "1,000/- and any amount",
        "monthly_aaum_date": "2 8   F E B R U A R Y   2 0 2 5",
        "monthly_avg_aum": "1,638.22 Crores",
        "mutual_fund_name": "",
        "page_number": [
            45
        ]
    },
    "bandhan liquid fund": {
        "amc_name": "",
        "benchmark_index": "NIFTY Liquid Index A-I (w.e.f. 1st April 2022)",
        "fund_manager": "Mr. Harshal Joshi (w.e.f. 15th September 2015) Mr. Brijesh Shah (w.e.f. 1st December 2021).",
        "inception_date": "2 July 2001",
        "load": {
            "exit_load": "Investor exit upon Exit load as a % of subscription redemption proceeds Day 1 0.0070% Day 2 0.0065% Day 3 0.0060% Day 4 0.0055% Day 5 0.0050% Day 6 0.0045% Day 7 onwards 0.0000% *With effect from October 20, 2019"
        },
        "main_scheme_name": "bandhan liquid fund",
        "metrics.average_maturity": "56",
        "metrics.macaulay_duration": "56",
        "metrics.modified_duration": "56",
        "metrics.standard_deviation": "0.14",
        "metrics.yield_to_maturity": "7.30",
        "minimum_investment": "100/- and any amount",
        "monthly_aaum_date": "2 8   F E B R U A R Y   2 0 2 5",
        "monthly_avg_aum": "16,156.89 Crores",
        "mutual_fund_name": "",
        "page_number": [
            46
        ]
    },
    "bandhan ultra short term fund": {
        "amc_name": "",
        "benchmark_index": "NIFTY Ultra Short Duration Debt Index A-I (w.e.f. 1st April 2022)",
        "fund_manager": "Mr. Harshal Joshi (w.e.f. 18th July 2018).",
        "inception_date": "18th July 2018",
        "load": {
            "exit_load": "Nil"
        },
        "main_scheme_name": "bandhan ultra short term fund",
        "metrics.average_maturity": "178",
        "metrics.macaulay_duration": "176",
        "metrics.modified_duration": "168",
        "metrics.standard_deviation": "0.15",
        "metrics.yield_to_maturity": "7.47",
        "minimum_investment": "100/- and any amount",
        "monthly_aaum_date": "2 8   F E B R U A R Y   2 0 2 5",
        "monthly_avg_aum": "3,937.91 Crores",
        "mutual_fund_name": "",
        "page_number": [
            47
        ]
    },
    "bandhan low duration fund": {
        "amc_name": "",
        "benchmark_index": "NIFTY Low Duration Debt Index A-I (w.e.f. 1st April 2022)",
        "fund_manager": "Mr. Harshal Joshi (w.e.f. 28th July 2021).",
        "inception_date": "17 January 2006",
        "load": {
            "exit_load": "Nil (Since 29th June 2012)"
        },
        "main_scheme_name": "bandhan low duration fund",
        "metrics.average_maturity": "375",
        "metrics.macaulay_duration": "347",
        "metrics.modified_duration": "333",
        "metrics.standard_deviation": "0.17",
        "metrics.yield_to_maturity": "7.43",
        "minimum_investment": "100/- and any amount",
        "monthly_aaum_date": "2 8   F E B R U A R Y   2 0 2 5",
        "monthly_avg_aum": "5,832.32 Crores",
        "mutual_fund_name": "",
        "page_number": [
            48
        ]
    },
    "bandhan money manager fund": {
        "amc_name": "",
        "benchmark_index": "NIFTY Money Market Index A-I (w.e.f. 1st April 2022)",
        "fund_manager": "Mr. Brijesh Shah (w.e.f. 12th July 2021) Mr. Gautam Kaul (w.e.f. 1st December 2021).",
        "inception_date": "18 February 2003",
        "load": {
            "exit_load": "Nil"
        },
        "main_scheme_name": "bandhan money manager fund",
        "metrics.average_maturity": "198",
        "metrics.macaulay_duration": "197",
        "metrics.modified_duration": "196",
        "metrics.standard_deviation": "0.17",
        "metrics.yield_to_maturity": "7.54",
        "minimum_investment": "100/- and any amount thereafter",
        "monthly_aaum_date": "2 8   F E B R U A R Y   2 0 2 5",
        "monthly_avg_aum": "10,001.30 Crores",
        "mutual_fund_name": "",
        "page_number": [
            49
        ]
    },
    "bandhan banking & psu debt fund": {
        "amc_name": "",
        "benchmark_index": "Nifty Banking & PSU Debt Index A-II (w.e.f. 12th March 2024)",
        "fund_manager": "Mr. Gautam Kaul (w.e.f. 1st December 2021) Mr. Suyash Choudhary (w.e.f. 28th July 2021).",
        "inception_date": "7 March 2013",
        "load": {
            "exit_load": "Nil (w.e.f. June 12th 2017)"
        },
        "main_scheme_name": "bandhan banking & psu debt fund",
        "metrics.average_maturity": "3.01",
        "metrics.macaulay_duration": "2.49",
        "metrics.modified_duration": "2.38",
        "metrics.standard_deviation": "0.53",
        "metrics.yield_to_maturity": "7.31",
        "minimum_investment": "1,000/- and any amount thereafter",
        "monthly_aaum_date": "2 8   F E B R U A R Y   2 0 2 5",
        "monthly_avg_aum": "13,492.92 Crores",
        "mutual_fund_name": "",
        "page_number": [
            50
        ]
    },
    "bandhan corporate bond fund": {
        "amc_name": "",
        "benchmark_index": "ModerateMoHdeigrhately Low to Moderate High Very Low High Riskometer The risk of the benchmark is low to moderate. Tier 2: NIFTY AAA Short Duration Bond Index",
        "fund_manager": "Mr. Gautam Kaul (w.e.f. 1st December 2021) Mr. Suyash Choudhary (w.e.f. 28th July 2021).",
        "inception_date": "12 January 2016",
        "load": {
            "exit_load": "Nil"
        },
        "main_scheme_name": "bandhan corporate bond fund",
        "metrics.average_maturity": "4.01",
        "metrics.macaulay_duration": "3.20",
        "metrics.modified_duration": "3.05",
        "metrics.standard_deviation": "0.70",
        "metrics.yield_to_maturity": "7.33",
        "minimum_investment": "1,000/- and any amount",
        "monthly_aaum_date": "2 8   F E B R U A R Y   2 0 2 5",
        "monthly_avg_aum": "13,831.67 Crores",
        "mutual_fund_name": "",
        "page_number": [
            51
        ]
    },
    "bandhan bond fund \u2013 short term plan": {
        "amc_name": "",
        "benchmark_index": "ModerateMoHdeigrhately Low to Moderate High Very Low High Riskometer The risk of the benchmark is low to moderate. Tier 2: NIFTY AAA Short Duration Bond Index",
        "fund_manager": "Mr. Suyash Choudhary (Since 11th March 2011).",
        "inception_date": "14 December 2000",
        "load": {
            "exit_load": "Nil (w.e.f. 23rd May 2016)"
        },
        "main_scheme_name": "bandhan bond fund \u2013 short term plan",
        "metrics.average_maturity": "3.54",
        "metrics.macaulay_duration": "3.00",
        "metrics.modified_duration": "2.89",
        "metrics.standard_deviation": "0.69",
        "metrics.yield_to_maturity": "7.25",
        "minimum_investment": "1,000/- and any amount",
        "monthly_aaum_date": "2 8   F E B R U A R Y   2 0 2 5",
        "monthly_avg_aum": "9,737.32 Crores",
        "mutual_fund_name": "",
        "page_number": [
            52
        ]
    },
    "bandhan bond fund \u2013 medium term plan": {
        "amc_name": "",
        "benchmark_index": "ModerateMoHdeigrhately Low to Moderate High Very Low High Riskometer The risk of the benchmark is moderate. Tier 2: NIFTY AAA Medium Duration Bond Index",
        "fund_manager": "Mr. Suyash Choudhary (w.e.f. 15th September 2015).",
        "inception_date": "8 July 2003",
        "load": {
            "exit_load": "NIL (w.e.f. 15th January 2019)"
        },
        "main_scheme_name": "bandhan bond fund \u2013 medium term plan",
        "metrics.average_maturity": "5.09",
        "metrics.macaulay_duration": "3.99",
        "metrics.modified_duration": "3.84",
        "metrics.standard_deviation": "1.01",
        "metrics.yield_to_maturity": "7.22",
        "minimum_investment": "1,000/- and any amount",
        "monthly_aaum_date": "2 8   F E B R U A R Y   2 0 2 5",
        "monthly_avg_aum": "1,477.91 Crores",
        "mutual_fund_name": "",
        "page_number": [
            53
        ]
    },
    "bandhan floating rate fund": {
        "amc_name": "",
        "benchmark_index": "NIFTY Short Duration Debt Index A-II (w.e.f. 12th March 2024)",
        "fund_manager": "Mr. Brijesh Shah & Mr. Debraj Lahiri (w.e.f. 14th March 2024).",
        "inception_date": "18 February 2021",
        "load": {
            "exit_load": "NIL"
        },
        "main_scheme_name": "bandhan floating rate fund",
        "metrics.average_maturity": "3.67",
        "metrics.macaulay_duration": "2.95",
        "metrics.modified_duration": "2.83",
        "metrics.standard_deviation": "0.61",
        "metrics.yield_to_maturity": "7.76",
        "minimum_investment": "Fresh 1,000/- and any amount thereafter",
        "monthly_aaum_date": "2 8   F E B R U A R Y   2 0 2 5",
        "monthly_avg_aum": "313.18 Crores",
        "mutual_fund_name": "",
        "page_number": [
            54
        ]
    },
    "bandhan credit risk fund": {
        "amc_name": "",
        "benchmark_index": "ModerateMoHdeigrhately Low to Moderate High Very Low High Riskometer The risk of the benchmark is moderately high. Tier 2: 65% NIFTY AA Short Duration Bond Index + 35% NIFTY AAA Short Duration Bond Index",
        "fund_manager": "Mr. Gautam Kaul (w.e.f. 16 July 2022) & Mr. Debraj Lahiri (w.e.f. 17 April 2023).",
        "inception_date": "03 March 2017",
        "load": {
            "exit_load": "1% if redeemed/switched out within 365 days from the date of allotment"
        },
        "main_scheme_name": "bandhan credit risk fund",
        "metrics.average_maturity": "3.64",
        "metrics.macaulay_duration": "2.73",
        "metrics.modified_duration": "2.59",
        "metrics.standard_deviation": "0.52",
        "metrics.yield_to_maturity": "7.91",
        "minimum_investment": "1,000/- and any amount",
        "monthly_aaum_date": "2 8   F E B R U A R Y   2 0 2 5",
        "monthly_avg_aum": "295.97 Crores",
        "mutual_fund_name": "",
        "page_number": [
            55
        ]
    },
    "bandhan bond fund \u2013 income plan": {
        "amc_name": "",
        "benchmark_index": "NIFTY Medium to Long Duration Debt Index A- III (w.e.f. 1st April 2022)",
        "fund_manager": "Mr. Suyash Choudhary (Since 15th October 2010).",
        "inception_date": "14 July 2000",
        "load": {
            "exit_load": "If redeemed/switched out within 365 days from the date of allotment: For 10% of investment : Nil, For remaining investment : 1% If redeemed/switched out after 365 days from the date of allotment: Nil"
        },
        "main_scheme_name": "bandhan bond fund \u2013 income plan",
        "metrics.average_maturity": "14.84",
        "metrics.macaulay_duration": "7.01",
        "metrics.modified_duration": "6.76",
        "metrics.standard_deviation": "1.91",
        "metrics.yield_to_maturity": "7.29",
        "minimum_investment": "1,000/- and any amount",
        "monthly_aaum_date": "2 8   F E B R U A R Y   2 0 2 5",
        "monthly_avg_aum": "484.08 Crores",
        "mutual_fund_name": "",
        "page_number": [
            56
        ]
    },
    "bandhan dynamic bond fund": {
        "amc_name": "",
        "benchmark_index": "NIFTY Composite Debt Index A-III (w.e.f. 1st April 2022)",
        "fund_manager": "Mr. Suyash Choudhary (Since 15th October 2010).",
        "inception_date": "25 June 2002",
        "load": {
            "exit_load": "Nil (w.e.f. 17th October 2016)"
        },
        "main_scheme_name": "bandhan dynamic bond fund",
        "metrics.average_maturity": "28.49",
        "metrics.macaulay_duration": "12.57",
        "metrics.modified_duration": "12.14",
        "metrics.standard_deviation": "3.81",
        "metrics.yield_to_maturity": "7.14",
        "minimum_investment": "1,000/- and any amount",
        "monthly_aaum_date": "2 8   F E B R U A R Y   2 0 2 5",
        "monthly_avg_aum": "3080.99 Crores",
        "mutual_fund_name": "",
        "page_number": [
            57
        ]
    },
    "bandhan long duration fund": {
        "amc_name": "",
        "benchmark_index": "NIFTY Long Duration Debt Index A-III",
        "fund_manager": "Mr. Gautam Kaul",
        "inception_date": "20 March 2024",
        "load": {
            "exit_load": "Nil"
        },
        "main_scheme_name": "bandhan long duration fund",
        "metrics.average_maturity": "28.66",
        "metrics.macaulay_duration": "12.45",
        "metrics.modified_duration": "12.03",
        "metrics.yield_to_maturity": "7.13",
        "minimum_investment": "1,000/- and any amount",
        "monthly_aaum_date": "2 8   F E B R U A R Y   2 0 2 5",
        "monthly_avg_aum": "211.22 Crores",
        "mutual_fund_name": "",
        "page_number": [
            58
        ]
    },
    "bandhan government securities fund - constant maturity plan": {
        "amc_name": "",
        "benchmark_index": "CRISIL 10 year Gilt Index (w.e.f. 28th May 2018)",
        "fund_manager": "Mr. Harshal Joshi (w.e.f. 15th May 2017).",
        "inception_date": "9 March 2002",
        "load": {
            "exit_load": "Nil."
        },
        "main_scheme_name": "bandhan government securities fund - constant maturity plan",
        "metrics.average_maturity": "10.68",
        "metrics.macaulay_duration": "7.38",
        "metrics.modified_duration": "7.14",
        "metrics.standard_deviation": "2.03",
        "metrics.yield_to_maturity": "6.95",
        "minimum_investment": "1,000/- and any amount",
        "monthly_aaum_date": "2 8   F E B R U A R Y   2 0 2 5",
        "monthly_avg_aum": "352.06 Crores",
        "mutual_fund_name": "",
        "page_number": [
            59
        ]
    },
    "bandhan government securities fund \u2013 investment plan": {
        "amc_name": "",
        "benchmark_index": "CRISIL Dynamic Gilt Index (w.e.f. 01 February 2019)",
        "fund_manager": "Mr. Suyash Choudhary (Since 15th October 2010).",
        "inception_date": "9 March 2002",
        "load": {
            "exit_load": "Nil (w.e.f. 15th July 2011)"
        },
        "main_scheme_name": "bandhan government securities fund \u2013 investment plan",
        "metrics.average_maturity": "28.47",
        "metrics.macaulay_duration": "12.56",
        "metrics.modified_duration": "12.13",
        "metrics.standard_deviation": "3.83",
        "metrics.yield_to_maturity": "7.14",
        "minimum_investment": "1,000/- and any amount",
        "monthly_aaum_date": "2 8   F E B R U A R Y   2 0 2 5",
        "monthly_avg_aum": "3,799.01 Crores",
        "mutual_fund_name": "",
        "page_number": [
            60
        ]
    },
    "bandhan nifty 50 index fund": {
        "amc_name": "",
        "benchmark_index": "Nifty 50 TRI",
        "fund_manager": "Mr. Nemish Sheth (w.e.f. March 01, 2022).",
        "inception_date": "30 April 2010",
        "load": {
            "exit_load": "NIL (w.e.f. 4th February 2019)"
        },
        "main_scheme_name": "bandhan nifty 50 index fund",
        "metrics.beta": "1.00",
        "metrics.r_squared": "1.00",
        "metrics.standard_deviation": "12.70",
        "minimum_investment": "1,000/- and any amount",
        "monthly_aaum_date": "2 8   F E B R U A R Y   2 0 2 5",
        "monthly_avg_aum": "1,671.09 Crores",
        "mutual_fund_name": "",
        "page_number": [
            61
        ]
    },
    "bandhan nifty 100 index fund": {
        "amc_name": "",
        "benchmark_index": "Nifty 100 TRI",
        "fund_manager": "Mr. Nemish Sheth",
        "inception_date": "24 February, 2022",
        "load": {
            "exit_load": "Nil"
        },
        "main_scheme_name": "bandhan nifty 100 index fund",
        "minimum_investment": "Rs 1,000/- in multiples of Re. 1/- thereafter",
        "monthly_aaum_date": "2 8   F E B R U A R Y   2 0 2 5",
        "monthly_avg_aum": "155.08 Crores",
        "mutual_fund_name": "",
        "page_number": [
            62
        ]
    },
    "bandhan nifty100 low volatility 30 index fund": {
        "amc_name": "",
        "benchmark_index": "Nifty100 Low Volatility 30 TRI",
        "fund_manager": "Mr. Nemish Sheth",
        "inception_date": "06 October, 2022",
        "load": {
            "exit_load": "Nil"
        },
        "main_scheme_name": "bandhan nifty100 low volatility 30 index fund",
        "minimum_investment": "Rs 1,000/- in multiples of Re. 1/- thereafter",
        "monthly_aaum_date": "2 8   F E B R U A R Y   2 0 2 5",
        "monthly_avg_aum": "1,385.39 Crores",
        "mutual_fund_name": "",
        "page_number": [
            63
        ]
    },
    "bandhan nifty200 momentum 30 index fund": {
        "amc_name": "",
        "benchmark_index": "Nifty200 Momentum 30 TRI",
        "fund_manager": "Mr. Nemish Sheth",
        "inception_date": "2 September, 2022",
        "load": {
            "exit_load": "Nil"
        },
        "main_scheme_name": "bandhan nifty200 momentum 30 index fund",
        "minimum_investment": "Rs 1,000/- in multiples of Re. 1/- thereafter",
        "monthly_aaum_date": "2 8   F E B R U A R Y   2 0 2 5",
        "monthly_avg_aum": "141.17 Crores",
        "mutual_fund_name": "",
        "page_number": [
            64
        ]
    },
    "bandhan nifty alpha 50 index fund": {
        "amc_name": "",
        "benchmark_index": "Nifty Alpha 50 Index TRI",
        "fund_manager": "Mr. Nemish Sheth",
        "inception_date": "09 November, 2023",
        "load": {
            "exit_load": "Nil"
        },
        "main_scheme_name": "bandhan nifty alpha 50 index fund",
        "minimum_investment": "Rs. 1,000/- and in multiples of Re. 1/- thereafter",
        "monthly_aaum_date": "2 8   F E B R U A R Y   2 0 2 5",
        "monthly_avg_aum": "347.96 Crores",
        "mutual_fund_name": "",
        "page_number": [
            65
        ]
    },
    "bandhan nifty smallcap 250 index fund": {
        "amc_name": "",
        "benchmark_index": "Nifty Smallcap 250 Index TRI",
        "fund_manager": "Mr. Nemish Sheth",
        "inception_date": "22 December, 2023",
        "load": {
            "exit_load": "Nil"
        },
        "main_scheme_name": "bandhan nifty smallcap 250 index fund",
        "minimum_investment": "Rs. 1,000/- and in multiples of Re. 1/- thereafter",
        "monthly_aaum_date": "2 8   F E B R U A R Y   2 0 2 5",
        "monthly_avg_aum": "47.12 Crores",
        "mutual_fund_name": "",
        "page_number": [
            66
        ]
    },
    "bandhan nifty it index fund": {
        "amc_name": "",
        "benchmark_index": "Nifty IT TRI",
        "fund_manager": "Mr. Nemish Sheth",
        "inception_date": "31 August, 2023",
        "load": {
            "exit_load": "Nil"
        },
        "main_scheme_name": "bandhan nifty it index fund",
        "minimum_investment": "Rs 1,000/- in multiples of Re. 1/- thereafter",
        "monthly_aaum_date": "2 8   F E B R U A R Y   2 0 2 5",
        "monthly_avg_aum": "28.93 Crores",
        "mutual_fund_name": "",
        "page_number": [
            67
        ]
    },
    "bandhan nifty total market index fund": {
        "amc_name": "",
        "benchmark_index": "Nifty Total Market TRI",
        "fund_manager": "Mr. Nemish Sheth",
        "inception_date": "10 July, 2024",
        "load": {
            "exit_load": " 0.25% if redeemed on or before 15 days from the allotment date.  Nil if redeemed after 15 days from allotment date."
        },
        "main_scheme_name": "bandhan nifty total market index fund",
        "minimum_investment": "Rs 1,000/- in multiples of Re. 1/- thereafter",
        "monthly_aaum_date": "2 8   F E B R U A R Y   2 0 2 5",
        "monthly_avg_aum": "36.39 Crores",
        "mutual_fund_name": "",
        "page_number": [
            68
        ]
    },
    "bandhan nifty bank index fund": {
        "amc_name": "",
        "benchmark_index": "Nifty Bank TRI",
        "fund_manager": "Mr. Nemish Sheth",
        "inception_date": "27 August, 2024",
        "load": {
            "exit_load": " 0.25% if redeemed on or before 15 days from the allotment date.  Nil if redeemed after 15 days from allotment date."
        },
        "main_scheme_name": "bandhan nifty bank index fund",
        "minimum_investment": "Rs 1,000/- in multiples of Re. 1/- thereafter",
        "monthly_aaum_date": "2 8   F E B R U A R Y   2 0 2 5",
        "monthly_avg_aum": "14.00 Crores",
        "mutual_fund_name": "",
        "page_number": [
            69
        ]
    },
    "bandhan bse healthcare index fund": {
        "amc_name": "",
        "benchmark_index": "BSE Healthcare TRI",
        "fund_manager": "Mr. Nemish Sheth",
        "inception_date": "06 September, 2024",
        "load": {
            "exit_load": " 0.25% if redeemed on or before 15 days from the allotment date.  Nil if redeemed after 15 days from allotment date."
        },
        "main_scheme_name": "bandhan bse healthcare index fund",
        "minimum_investment": "Rs 1,000/- in multiples of Re. 1/- thereafter",
        "monthly_aaum_date": "2 8   F E B R U A R Y   2 0 2 5",
        "monthly_avg_aum": "18.04 Crores",
        "mutual_fund_name": "",
        "page_number": [
            70
        ]
    },
    "bandhan nifty midcap 150 index fund": {
        "amc_name": "",
        "benchmark_index": "Nifty Midcap 150 TRI",
        "fund_manager": "Mr. Nemish Sheth",
        "inception_date": "19 September, 2024",
        "load": {
            "exit_load": " 0.25% if redeemed on or before 15 days from the allotment date.  Nil if redeemed after 15 days from allotment date."
        },
        "main_scheme_name": "bandhan nifty midcap 150 index fund",
        "minimum_investment": "Rs 1,000/- in multiples of Re. 1/- thereafter",
        "monthly_aaum_date": "2 8   F E B R U A R Y   2 0 2 5",
        "monthly_avg_aum": "21.10 Crores",
        "mutual_fund_name": "",
        "page_number": [
            71
        ]
    },
    "bandhan nifty 500 momentum 50 index fund": {
        "amc_name": "",
        "benchmark_index": "Nifty 500 Momentum 50 TRI",
        "fund_manager": "Mr. Nemish Sheth",
        "inception_date": "30 October, 2024",
        "load": {
            "exit_load": " 0.25% if redeemed on or before 15 days from the allotment date.  Nil if redeemed after 15 days from allotment date."
        },
        "main_scheme_name": "bandhan nifty 500 momentum 50 index fund",
        "minimum_investment": "Rs 1,000/- in multiples of Re. 1/- thereafter",
        "monthly_aaum_date": "2 8   F E B R U A R Y   2 0 2 5",
        "monthly_avg_aum": "15.72 Crores",
        "mutual_fund_name": "",
        "page_number": [
            72
        ]
    },
    "bandhan nifty 500 value 50 index fund": {
        "amc_name": "",
        "benchmark_index": "Nifty 500 Value 50 TRI",
        "fund_manager": "Mr. Nemish Sheth",
        "inception_date": "30 October, 2024",
        "load": {
            "exit_load": " 0.25% if redeemed on or before 15 days from the allotment date.  Nil if redeemed after 15 days from allotment date."
        },
        "main_scheme_name": "bandhan nifty 500 value 50 index fund",
        "minimum_investment": "Rs 1,000/- in multiples of Re. 1/- thereafter",
        "monthly_aaum_date": "2 8   F E B R U A R Y   2 0 2 5",
        "monthly_avg_aum": "8.23 Crores",
        "mutual_fund_name": "",
        "page_number": [
            73
        ]
    },
    "bandhan nifty 200 quality 30 index fund": {
        "amc_name": "",
        "benchmark_index": "Nifty 200 Quality 30 TRI",
        "fund_manager": "Mr. Nemish Sheth",
        "inception_date": "04 December, 2024",
        "load": {
            "exit_load": " 0.25% if redeemed on or before 15 days from the allotment date.  Nil if redeemed after 15 days from allotment date."
        },
        "main_scheme_name": "bandhan nifty 200 quality 30 index fund",
        "minimum_investment": "Rs 1,000/- in multiples of Re. 1/- thereafter",
        "monthly_aaum_date": "2 8   F E B R U A R Y   2 0 2 5",
        "monthly_avg_aum": "7.60 Crores",
        "mutual_fund_name": "",
        "page_number": [
            74
        ]
    },
    "bandhan bse sensex etf": {
        "amc_name": "",
        "benchmark_index": "BSE Sensex TRI",
        "fund_manager": "Mr. Nemish Sheth (w.e.f 1 November 2021)",
        "inception_date": "07 October 2016",
        "load": {
            "exit_load": "Nil"
        },
        "main_scheme_name": "bandhan bse sensex etf",
        "metrics.beta": "1.00",
        "metrics.r_squared": "1.00",
        "metrics.standard_deviation": "12.36",
        "monthly_aaum_date": "2 8   F E B R U A R Y   2 0 2 5",
        "monthly_avg_aum": "1.21 Crores",
        "mutual_fund_name": "",
        "page_number": [
            75
        ]
    },
    "bandhan nifty 50 etf": {
        "amc_name": "",
        "benchmark_index": "Nifty 50 TRI",
        "fund_manager": "Mr. Nemish Sheth (w.e.f 1 November 2021)",
        "inception_date": "07 October 2016",
        "load": {
            "exit_load": "Nil"
        },
        "main_scheme_name": "bandhan nifty 50 etf",
        "metrics.beta": "1.00",
        "metrics.r_squared": "1.00",
        "metrics.standard_deviation": "12.70",
        "monthly_aaum_date": "2 8   F E B R U A R Y   2 0 2 5",
        "monthly_avg_aum": "26.64 Crores",
        "mutual_fund_name": "",
        "page_number": [
            76
        ]
    },
    "bandhan crisil ibx gilt april 2026 index fund": {
        "amc_name": "",
        "benchmark_index": "CRISIL IBX Gilt Index - April 2026",
        "fund_manager": "Mr. Gautam Kaul",
        "inception_date": "20 October, 2022",
        "load": {
            "exit_load": "Nil"
        },
        "main_scheme_name": "bandhan crisil ibx gilt april 2026 index fund",
        "metrics.average_maturity": "1.19",
        "metrics.macaulay_duration": "1.15",
        "metrics.modified_duration": "1.11",
        "metrics.standard_deviation": "0.40",
        "metrics.yield_to_maturity": "6.80",
        "minimum_investment": "1,000/- and in multiples of Re. 1/- thereafter",
        "monthly_aaum_date": "2 8   F E B R U A R Y   2 0 2 5",
        "monthly_avg_aum": "471.77 Crores",
        "mutual_fund_name": "",
        "page_number": [
            77
        ]
    },
    "bandhan crisil ibx gilt june 2027 index fund": {
        "amc_name": "",
        "benchmark_index": "CRISIL-IBX Gilt Index - June 2027",
        "fund_manager": "Mr. Harshal Joshi (w.e.f. 28th July 2021) Mr. Gautam Kaul (w.e.f. 1st December 2021)",
        "inception_date": "23 March 2021",
        "load": {
            "exit_load": "Nil"
        },
        "main_scheme_name": "bandhan crisil ibx gilt june 2027 index fund",
        "metrics.average_maturity": "2.36",
        "metrics.macaulay_duration": "2.19",
        "metrics.modified_duration": "2.12",
        "metrics.standard_deviation": "0.75",
        "metrics.yield_to_maturity": "6.82",
        "minimum_investment": "1,000/- and any amount",
        "monthly_aaum_date": "2 8   F E B R U A R Y   2 0 2 5",
        "monthly_avg_aum": "7,072.29 Crores",
        "mutual_fund_name": "",
        "page_number": [
            78
        ]
    },
    "bandhan crisil ibx gilt april 2028 index fund": {
        "amc_name": "",
        "benchmark_index": "CRISIL-IBX Gilt Index - April 2028",
        "fund_manager": "Mr. Harshal Joshi (w.e.f. 28th July 2021) Mr. Gautam Kaul (w.e.f. 1st December 2021)",
        "inception_date": "23 March 2021",
        "load": {
            "exit_load": "Nil"
        },
        "main_scheme_name": "bandhan crisil ibx gilt april 2028 index fund",
        "metrics.average_maturity": "2.87",
        "metrics.macaulay_duration": "2.56",
        "metrics.modified_duration": "2.48",
        "metrics.standard_deviation": "0.83",
        "metrics.yield_to_maturity": "6.83",
        "minimum_investment": "1,000/- and any amount",
        "monthly_aaum_date": "2 8   F E B R U A R Y   2 0 2 5",
        "monthly_avg_aum": "4,720.36 Crores",
        "mutual_fund_name": "",
        "page_number": [
            79
        ]
    },
    "bandhan crisil ibx gilt april 2032 index fund": {
        "amc_name": "",
        "benchmark_index": "Crisil IBX Gilt Index - April 2032",
        "fund_manager": "Mr. Harshal Joshi & Mr. Gautam Kaul",
        "inception_date": "15 February 2023",
        "load": {
            "exit_load": "Nil"
        },
        "main_scheme_name": "bandhan crisil ibx gilt april 2032 index fund",
        "metrics.average_maturity": "6.90",
        "metrics.macaulay_duration": "5.49",
        "metrics.modified_duration": "5.31",
        "metrics.standard_deviation": "1.73",
        "metrics.yield_to_maturity": "6.90",
        "minimum_investment": "1,000/- and in multiples of Re. 1/- thereafter",
        "monthly_aaum_date": "2 8   F E B R U A R Y   2 0 2 5",
        "monthly_avg_aum": "435.87 Crores",
        "mutual_fund_name": "",
        "page_number": [
            80
        ]
    },
    "bandhan crisil ibx 90:10 sdl plus gilt\u2013 november 2026 index fund": {
        "amc_name": "",
        "benchmark_index": "CRISIL IBX 90:10 SDL plus Gilt Index  November 2026",
        "fund_manager": "Mr. Gautam Kaul & Mr. Harshal Joshi",
        "inception_date": "17 November, 2022",
        "load": {
            "exit_load": "Nil"
        },
        "main_scheme_name": "bandhan crisil ibx 90:10 sdl plus gilt\u2013 november 2026 index fund",
        "metrics.average_maturity": "1.73",
        "metrics.macaulay_duration": "1.63",
        "metrics.modified_duration": "1.58",
        "metrics.standard_deviation": "0.44",
        "metrics.yield_to_maturity": "7.03",
        "minimum_investment": "1,000/- and in multiples of Re. 1/- thereafter",
        "monthly_aaum_date": "2 8   F E B R U A R Y   2 0 2 5",
        "monthly_avg_aum": "114.28 Crores",
        "mutual_fund_name": "",
        "page_number": [
            81
        ]
    },
    "bandhan crisil ibx 90:10 sdl plus gilt\u2013 september 2027 index fund": {
        "amc_name": "",
        "benchmark_index": "CRISIL IBX 90:10 SDL plus Gilt Index  September 2027",
        "fund_manager": "Mr. Gautam Kaul & Mr. Harshal Joshi",
        "inception_date": "24 November, 2022",
        "load": {
            "exit_load": "Nil"
        },
        "main_scheme_name": "bandhan crisil ibx 90:10 sdl plus gilt\u2013 september 2027 index fund",
        "metrics.average_maturity": "2.55",
        "metrics.macaulay_duration": "2.31",
        "metrics.modified_duration": "2.23",
        "metrics.standard_deviation": "0.58",
        "metrics.yield_to_maturity": "7.07",
        "minimum_investment": "1,000/- and in multiples of Re. 1/- thereafter",
        "monthly_aaum_date": "2 8   F E B R U A R Y   2 0 2 5",
        "monthly_avg_aum": "150.28 Crores",
        "mutual_fund_name": "",
        "page_number": [
            82
        ]
    }
}